{
  "cli": {
    "version": ">= 9.0.0",
    "appVersionSource": "remote"
  },
  "build": {
    "development": {
      "developmentClient": true,
      "distribution": "internal",
      "android": { "buildType": "apk" },
      "env": {
        "EXPO_PUBLIC_API_BASE_URL": "https://nikesh2290-krishisaathi-backend.hf.space",
        "EXPO_PUBLIC_USE_NATIVE_GEMMA": "1",
        "EXPO_PUBLIC_SUPABASE_URL": "https://ivwnljoodlmpgbbfekdk.supabase.co"
      }
    },
    "preview": {
      "android": { "buildType": "apk" },
      "distribution": "internal",
      "env": {
        "EXPO_PUBLIC_API_BASE_URL": "https://nikesh2290-krishisaathi-backend.hf.space",
        "EXPO_PUBLIC_USE_NATIVE_GEMMA": "1",
        "EXPO_PUBLIC_SUPABASE_URL": "https://ivwnljoodlmpgbbfekdk.supabase.co"
      }
    },
    "production": {
      "android": { "buildType": "apk" },
      "distribution": "internal",
      "env": {
        "EXPO_PUBLIC_API_BASE_URL": "https://nikesh2290-krishisaathi-backend.hf.space",
        "EXPO_PUBLIC_USE_NATIVE_GEMMA": "1",
        "EXPO_PUBLIC_SUPABASE_URL": "https://ivwnljoodlmpgbbfekdk.supabase.co"
      }
    }
  },
  "submit": {
    "production": {
      "android": { "track": "internal" }
    }
  }
}
